adv_bible_search-0.1.1.dist-info/licenses/LICENSE
bible_search/__init__.py
bible_search/bible_search.py
bible_search/database.py
bible_search/fuzzy_search.py
bible_search/search_cli.py
bible_search/semantic_search.py
adv_bible_search-0.1.1.dist-info/METADATA
adv_bible_search-0.1.1.dist-info/WHEEL
adv_bible_search-0.1.1.dist-info/entry_points.txt
adv_bible_search-0.1.1.dist-info/top_level.txt
adv_bible_search-0.1.1.dist-info/RECORD
