Metadata-Version: 2.4
Name: adv-bible-search
Version: 0.1.1
Summary: Advanced Bible Search Library with fuzzy and semantic search capabilities
Home-page: https://github.com/siroosab/bible-search
Author: Mahboob
Author-email: siroosab@example.com
Classifier: Programming Language :: Python :: 3
Classifier: License :: OSI Approved :: MIT License
Classifier: Operating System :: OS Independent
Requires-Python: >=3.8
License-File: LICENSE
Requires-Dist: rapidfuzz
Requires-Dist: sentence-transformers>=2.2.2
Requires-Dist: huggingface-hub<0.14.0
Requires-Dist: transformers<4.30.0
Requires-Dist: tqdm
Requires-Dist: numpy
Requires-Dist: pandas
Requires-Dist: torch
Requires-Dist: whoosh
Dynamic: author
Dynamic: author-email
Dynamic: classifier
Dynamic: description
Dynamic: description-content-type
Dynamic: home-page
Dynamic: license-file
Dynamic: requires-dist
Dynamic: requires-python
Dynamic: summary
